{
    "chw @ cle": {
        "carlos santana": {
            "pn": "535/-979"
        },
        "jose ramirez": {
            "pn": "436/-722"
        },
        "matt thaiss": {
            "pn": "844/-2063"
        },
        "mike tauchman": {
            "pn": "827/-1989"
        },
        "nick maton": {
            "pn": "727/-1598"
        },
        "nolan jones": {
            "pn": "784/-1814"
        },
        "bo naylor": {
            "pn": "696/-1484"
        },
        "gabriel arias": {
            "pn": "712/-1543"
        },
        "luis robert": {
            "pn": "635/-1279"
        },
        "miguel vargas": {
            "pn": "895/-2286"
        },
        "andrew vaughn": {
            "pn": "653/-1337"
        },
        "kyle manzardo": {
            "pn": "576/-1097"
        }
    },
    "phi @ atl": {
        "bryce harper": {
            "pn": "436/-722"
        },
        "nick castellanos": {
            "pn": "690/-1463"
        },
        "jt realmuto": {
            "pn": "767/-1749"
        },
        "max kepler": {
            "pn": "604/-1181"
        },
        "trea turner": {
            "pn": "612/-1208"
        },
        "kyle schwarber": {
            "pn": "355/-541"
        },
        "alec bohm": {
            "pn": "843/-2055"
        },
        "brandon marsh": {
            "pn": "783/-1811"
        },
        "marcell ozuna": {
            "pn": "384/-603"
        },
        "orlando arcia": {
            "pn": "640/-1296"
        },
        "matt olson": {
            "pn": "500/-882"
        },
        "eli white": {
            "pn": "887/-2251"
        },
        "ozzie albies": {
            "pn": "555/-1029"
        },
        "bryan de la cruz": {
            "pn": "679/-1425"
        },
        "austin riley": {
            "pn": "349/-529"
        },
        "sean murphy": {
            "pn": "500/-882"
        },
        "michael harris": {
            "pn": "840/-2044"
        }
    },
    "laa @ tb": {
        "yandy diaz": {
            "pn": "663/-1372"
        },
        "brandon lowe": {
            "pn": "486/-846"
        },
        "jonathan aranda": {
            "pn": "585/-1124"
        },
        "christopher morel": {
            "pn": "631/-1267"
        },
        "kameron misner": {
            "pn": "752/-1691"
        },
        "junior caminero": {
            "pn": "540/-993"
        },
        "mike trout": {
            "pn": "314/-458"
        },
        "taylor ward": {
            "pn": "458/-775"
        },
        "jorge soler": {
            "pn": "328/-486"
        },
        "luis rengifo": {
            "pn": "751/-1685"
        },
        "jo adell": {
            "pn": "461/-783"
        },
        "kyren paris": {
            "pn": "879/-2216"
        },
        "logan ohoppe": {
            "pn": "442/-736"
        },
        "nolan schanuel": {
            "pn": "782/-1808"
        }
    },
    "tor @ bos": {
        "george springer": {
            "pn": "747/-1672"
        },
        "anthony santander": {
            "pn": "496/-871"
        },
        "vladimir guerrero": {
            "pn": "651/-1333"
        },
        "bo bichette": {
            "pn": "837/-2033"
        },
        "alan roden": {
            "pn": "868/-2166"
        },
        "trevor story": {
            "pn": "754/-1699"
        },
        "alex bregman": {
            "pn": "634/-1277"
        },
        "rafael devers": {
            "pn": "384/-603"
        },
        "triston casas": {
            "pn": "655/-1346"
        },
        "wilyer abreu": {
            "pn": "456/-770"
        },
        "ceddanne rafaela": {
            "pn": "917/-2390"
        },
        "jarren duran": {
            "pn": "607/-1190"
        }
    },
    "min @ kc": {
        "salvador perez": {
            "pn": "439/-728"
        },
        "hunter renfroe": {
            "pn": "655/-1344"
        },
        "carlos correa": {
            "pn": "776/-1781"
        },
        "byron buxton": {
            "pn": "377/-587"
        },
        "trevor larnach": {
            "pn": "675/-1411"
        },
        "jonathan india": {
            "pn": "621/-1234"
        },
        "ty france": {
            "pn": "901/-2314"
        },
        "mj melendez": {
            "pn": "618/-1226"
        },
        "jose miranda": {
            "pn": "872/-2182"
        },
        "matt wallner": {
            "pn": "382/-599"
        },
        "bobby witt": {
            "pn": "446/-745"
        },
        "ryan jeffers": {
            "pn": "744/-1659"
        },
        "vinnie pasquantino": {
            "pn": "608/-1193"
        },
        "michael massey": {
            "pn": "624/-1244"
        }
    }
}