{
    "laa @ atl": {
        "lucas giolito": {
            "k": "o5.5 108/-138"
        },
        "yonny chirinos": {
            "k": "o3.5 -126/-102"
        },
        "ronald acuna": {
            "double": 260,
            "hr": 340,
            "single": -165,
            "h": -370
        },
        "mickey moniak": {
            "double": 300,
            "hr": 440,
            "single": -175,
            "h": -340,
            "triple": 2000
        },
        "shohei ohtani": {
            "double": 310,
            "hr": 240,
            "single": -115,
            "h": -310,
            "triple": 2000
        },
        "luis rengifo": {
            "double": 330,
            "hr": 630,
            "single": -160,
            "h": -270,
            "triple": 3200
        },
        "ozzie albies": {
            "double": 350,
            "hr": 470,
            "single": -115,
            "h": -240,
            "triple": 2900
        },
        "austin riley": {
            "double": 370,
            "hr": 340,
            "single": -105,
            "h": -240
        },
        "hunter renfroe": {
            "double": 370,
            "hr": 440,
            "single": -120,
            "h": -240
        },
        "cj cron": {
            "double": 370,
            "hr": 420,
            "single": -110,
            "h": -230
        },
        "travis darnaud": {
            "double": 380,
            "hr": 500,
            "single": -105,
            "h": -200
        },
        "mike moustakas": {
            "double": 400,
            "hr": 430,
            "single": -115,
            "h": -230
        },
        "orlando arcia": {
            "double": 410,
            "hr": 680,
            "single": -110,
            "h": -190
        },
        "randal grichuk": {
            "double": 410,
            "hr": 540,
            "single": -115,
            "h": -210,
            "triple": 3900
        },
        "michael harris": {
            "double": 430,
            "hr": 750,
            "single": -115,
            "h": -190,
            "triple": 3400
        },
        "marcell ozuna": {
            "double": 430,
            "hr": 360,
            "single": 110,
            "h": -195
        },
        "zach neto": {
            "double": 430,
            "hr": 600,
            "single": 100,
            "h": -185,
            "triple": 3000
        },
        "chad wallach": {
            "double": 480,
            "hr": 600,
            "single": 105,
            "h": -170
        },
        "matt olson": {
            "double": 490,
            "hr": 255,
            "single": 110,
            "h": -230
        },
        "eddie rosario": {
            "double": 500,
            "hr": 480,
            "single": 110,
            "h": -170,
            "triple": 4000
        }
    },
    "det @ pit": {
        "osvaldo bido": {
            "k": "o4.5 -122/-104"
        },
        "eduardo rodriguez": {
            "k": "o5.5 -128/102"
        },
        "matt vierling": {
            "single": -180,
            "double": 320,
            "hr": 1060,
            "h": -290,
            "triple": 1900
        },
        "riley greene": {
            "single": -165,
            "double": 330,
            "hr": 630,
            "h": -290,
            "triple": 2400
        },
        "zach mckinstry": {
            "single": -160,
            "double": 330,
            "hr": 830,
            "h": -270,
            "triple": 1700
        },
        "josh palacios": {
            "single": -145,
            "double": 370,
            "hr": 870,
            "h": -240,
            "triple": 3100
        },
        "javier baez": {
            "single": -135,
            "double": 330,
            "hr": 870,
            "h": -230,
            "triple": 2900
        },
        "kebryan hayes": {
            "single": -135,
            "double": 310,
            "hr": 800,
            "h": -240,
            "triple": 2900
        },
        "bryan reynolds": {
            "single": -125,
            "double": 280,
            "hr": 700,
            "h": -250,
            "triple": 2400
        },
        "kerry carpenter": {
            "single": -125,
            "double": 390,
            "hr": 600,
            "h": -220,
            "triple": 2700
        },
        "spencer torkelson": {
            "single": -120,
            "double": 340,
            "hr": 500,
            "h": -230
        },
        "henry davis": {
            "single": -120,
            "double": 330,
            "hr": 800,
            "h": -210
        },
        "andrew mccutchen": {
            "single": -110,
            "double": 320,
            "hr": 680,
            "h": -210
        },
        "endy rodriguez": {
            "single": -105,
            "double": 350,
            "hr": 870,
            "h": -185,
            "triple": 4600
        },
        "zack short": {
            "single": 100,
            "double": 410,
            "hr": 1000,
            "h": -165
        },
        "connor joe": {
            "single": 100,
            "double": 380,
            "hr": 870,
            "h": -175,
            "triple": 2900
        },
        "akil baddoo": {
            "single": 115,
            "double": 500,
            "hr": 900,
            "h": -145,
            "triple": 2900
        },
        "nick gonzales": {
            "single": 110,
            "double": 400,
            "hr": 900,
            "h": -165,
            "triple": 2900
        },
        "jake rogers": {
            "single": 135,
            "double": 500,
            "hr": 750,
            "h": -135
        },
        "liover peguero": {
            "single": 135,
            "double": 460,
            "hr": 1000,
            "h": -135,
            "triple": 2800
        }
    },
    "mil @ wsh": {
        "wade miley": {
            "k": "o3.5 -136/108"
        },
        "mackenzie gore": {
            "k": "o5.5 -120/-106"
        },
        "cj abrams": {
            "single": -175,
            "triple": 2400,
            "double": 340,
            "h": -270,
            "hr": 1060
        },
        "joey meneses": {
            "single": -160,
            "double": 280,
            "h": -290,
            "hr": 560
        },
        "owen miller": {
            "single": -160,
            "double": 260,
            "h": -280,
            "hr": 830
        },
        "dominic smith": {
            "single": -160,
            "double": 460,
            "h": -230,
            "hr": 1000
        },
        "andruw monasterio": {
            "single": -155,
            "triple": 4800,
            "double": 320,
            "h": -250,
            "hr": 900
        },
        "christian yelich": {
            "single": -145,
            "triple": 3800,
            "double": 290,
            "h": -270,
            "hr": 630
        },
        "william contreras": {
            "single": -140,
            "double": 250,
            "h": -290,
            "hr": 450
        },
        "ildemaro vargas": {
            "single": -135,
            "triple": 3400,
            "double": 380,
            "h": -220,
            "hr": 870
        },
        "brice turang": {
            "single": -130,
            "triple": 1900,
            "double": 440,
            "h": -210,
            "hr": 870
        },
        "stone garrett": {
            "single": -120,
            "triple": 4200,
            "double": 290,
            "h": -250,
            "hr": 480
        },
        "willy adames": {
            "single": -115,
            "double": 310,
            "h": -250,
            "hr": 400
        },
        "lane thomas": {
            "single": -110,
            "triple": 3600,
            "double": 280,
            "h": -230,
            "hr": 560
        },
        "michael chavis": {
            "single": 110,
            "triple": 4100,
            "double": 390,
            "h": -170,
            "hr": 750
        },
        "alex call": {
            "single": 110,
            "triple": 4800,
            "double": 420,
            "h": -155,
            "hr": 900
        },
        "tyrone taylor": {
            "single": 110,
            "triple": 3100,
            "double": 340,
            "h": -175,
            "hr": 680
        },
        "riley adams": {
            "single": 125,
            "triple": 3500,
            "double": 400,
            "h": -160,
            "hr": 630
        },
        "blake perkins": {
            "single": 130,
            "triple": 1700,
            "double": 500,
            "h": -145,
            "hr": 870
        },
        "joey wiemer": {
            "single": 135,
            "triple": 1700,
            "double": 380,
            "h": -160,
            "hr": 630
        }
    },
    "sd @ col": {
        "kyle freeland": {
            "k": "o3.5 122/-154"
        },
        "joe musgrove": {
            "k": "o6.5 126/-160"
        },
        "fernando tatis": {
            "double": 195,
            "hr": 200,
            "h": -600,
            "single": -185,
            "triple": 1800
        },
        "ha seong kim": {
            "double": 200,
            "hr": 400,
            "h": -470,
            "single": -200,
            "triple": 1900
        },
        "manny machado": {
            "double": 230,
            "hr": 290,
            "h": -400,
            "single": -160,
            "triple": 2900
        },
        "jurickson profar": {
            "double": 240,
            "hr": 900,
            "h": -310,
            "single": -165,
            "triple": 1800
        },
        "brendan rodgers": {
            "double": 240,
            "hr": 630,
            "h": -410,
            "single": -195,
            "triple": 1800
        },
        "ezequiel tovar": {
            "double": 240,
            "hr": 700,
            "h": -360,
            "single": -175,
            "triple": 950
        },
        "xander bogaerts": {
            "double": 250,
            "hr": 560,
            "h": -330,
            "single": -170,
            "triple": 3200
        },
        "luis campusano": {
            "double": 250,
            "hr": 460,
            "h": -380,
            "single": -185,
            "triple": 3000
        },
        "jake cronenworth": {
            "double": 270,
            "hr": 750,
            "h": -310,
            "single": -150,
            "triple": 850
        },
        "juan soto": {
            "double": 300,
            "hr": 285,
            "h": -330,
            "single": -140,
            "triple": 2200
        },
        "elias diaz": {
            "double": 340,
            "hr": 560,
            "h": -250,
            "single": -135,
            "triple": 3200
        },
        "gary sanchez": {
            "double": 340,
            "hr": 350,
            "h": -230,
            "single": -105
        },
        "brenton doyle": {
            "double": 380,
            "hr": 800,
            "h": -230,
            "single": -110,
            "triple": 800
        },
        "ryan mcmahon": {
            "double": 390,
            "hr": 520,
            "h": -195,
            "single": 105,
            "triple": 2000
        },
        "elehuris montero": {
            "double": 410,
            "hr": 750,
            "h": -210,
            "single": -125,
            "triple": 3300
        },
        "nolan jones": {
            "double": 420,
            "hr": 480,
            "h": -230,
            "single": -110,
            "triple": 1200
        },
        "trent grisham": {
            "double": 430,
            "hr": 520,
            "h": -185,
            "single": 105,
            "triple": 1900
        },
        "michael toglia": {
            "double": 440,
            "hr": 600,
            "h": -170,
            "single": 125,
            "triple": 1200
        }
    },
    "bos @ sea": {
        "kutter crawford": {
            "k": "o5.5 120/-152"
        },
        "logan gilbert": {
            "k": "o5.5 -138/108"
        },
        "jarren duran": {
            "double": 320,
            "triple": 2700,
            "h": -250,
            "single": -145,
            "hr": 630
        },
        "masataka yoshida": {
            "double": 320,
            "triple": 3100,
            "h": -290,
            "single": -170,
            "hr": 870
        },
        "rafael devers": {
            "double": 360,
            "h": -230,
            "single": -110,
            "hr": 360
        },
        "julio rodriguez": {
            "double": 380,
            "h": -260,
            "single": -125,
            "hr": 350
        },
        "justin turner": {
            "double": 410,
            "h": -230,
            "single": -135,
            "hr": 540
        },
        "jp crawford": {
            "double": 410,
            "h": -220,
            "single": -140,
            "hr": 830
        },
        "alex verdugo": {
            "double": 420,
            "h": -240,
            "single": -150,
            "hr": 700
        },
        "teoscar hernandez": {
            "double": 440,
            "h": -200,
            "single": 100,
            "hr": 400
        },
        "cal raleigh": {
            "double": 460,
            "h": -195,
            "single": 115,
            "hr": 340
        },
        "ty france": {
            "double": 470,
            "h": -195,
            "single": -120,
            "hr": 700
        },
        "connor wong": {
            "double": 470,
            "h": -170,
            "single": -105,
            "hr": 800
        },
        "adam duvall": {
            "double": 480,
            "h": -165,
            "single": 125,
            "hr": 370
        },
        "eugenio suarez": {
            "double": 500,
            "h": -160,
            "single": 135,
            "hr": 370
        },
        "cade marlowe": {
            "double": 500,
            "triple": 4500,
            "h": -140,
            "single": 125,
            "hr": 900
        },
        "triston casas": {
            "double": 500,
            "triple": 4800,
            "h": -140,
            "single": 150,
            "hr": 420
        },
        "josh rojas": {
            "double": 500,
            "h": -155,
            "single": 105,
            "hr": 680
        },
        "mike ford": {
            "double": 600,
            "h": -130,
            "single": 145,
            "hr": 560
        },
        "yu chang": {
            "double": 650,
            "h": -120,
            "single": 150,
            "hr": 680
        }
    },
    "phi @ mia": {
        "braxton garrett": {
            "k": "o6.5 120/-152"
        },
        "zack wheeler": {
            "k": "o6.5 -138/108"
        },
        "luis arraez": {
            "single": -230,
            "double": 350,
            "h": -350,
            "hr": 1100,
            "triple": 2800
        },
        "bryson stott": {
            "single": -170,
            "double": 410,
            "h": -270,
            "hr": 750,
            "triple": 3000
        },
        "alec bohm": {
            "single": -155,
            "double": 290,
            "h": -280,
            "hr": 700,
            "triple": 4700
        },
        "trea turner": {
            "single": -150,
            "double": 290,
            "h": -280,
            "hr": 750,
            "triple": 2100
        },
        "nick castellanos": {
            "single": -130,
            "double": 300,
            "h": -250,
            "hr": 600,
            "triple": 3200
        },
        "joey wendle": {
            "single": -120,
            "double": 490,
            "h": -185,
            "hr": 1100,
            "triple": 2500
        },
        "bryce harper": {
            "single": -110,
            "double": 410,
            "h": -195,
            "hr": 600,
            "triple": 3800
        },
        "bryan de la cruz": {
            "single": -105,
            "double": 390,
            "h": -180,
            "hr": 900
        },
        "jazz chisholm": {
            "single": 105,
            "double": 480,
            "h": -185,
            "hr": 540,
            "triple": 2000
        },
        "jon berti": {
            "single": 105,
            "double": 500,
            "h": -160,
            "hr": 900,
            "triple": 2800
        },
        "josh bell": {
            "single": 105,
            "double": 440,
            "h": -175,
            "hr": 600
        },
        "edmundo sosa": {
            "single": 115,
            "double": 480,
            "h": -155,
            "hr": 900,
            "triple": 1900
        },
        "jorge soler": {
            "single": 120,
            "double": 470,
            "h": -165,
            "hr": 500
        },
        "jacob stallings": {
            "single": 120,
            "double": 550,
            "h": -130,
            "hr": 1060
        },
        "kyle schwarber": {
            "single": 145,
            "double": 550,
            "h": -150,
            "hr": 420,
            "triple": 3100
        },
        "johan rojas": {
            "single": 145,
            "double": 650,
            "h": -120,
            "hr": 1100,
            "triple": 1500
        },
        "jake burger": {
            "single": 140,
            "double": 500,
            "h": -150,
            "hr": 480,
            "triple": 3000
        },
        "garrett stubbs": {
            "single": 155,
            "double": 750,
            "h": 100,
            "hr": 1100
        }
    },
    "tb @ nyy": {
        "shane mcclanahan": {
            "k": "o6.5 120/-152"
        },
        "gerrit cole": {
            "k": "o7.5 -116/-110"
        },
        "wander franco": {
            "double": 370,
            "hr": 600,
            "h": -270,
            "single": -150,
            "triple": 2700
        },
        "yandy diaz": {
            "double": 410,
            "hr": 500,
            "h": -250,
            "single": -145
        },
        "gleyber torres": {
            "double": 450,
            "hr": 450,
            "h": -210,
            "single": -110
        },
        "isiah kiner falefa": {
            "double": 450,
            "hr": 870,
            "h": -230,
            "single": -155
        },
        "dj lemahieu": {
            "double": 460,
            "hr": 700,
            "h": -185,
            "single": -110
        },
        "randy arozarena": {
            "double": 490,
            "hr": 500,
            "h": -180,
            "single": 100,
            "triple": 4000
        },
        "aaron judge": {
            "double": 490,
            "hr": 285,
            "h": -220,
            "single": 110
        },
        "harrison bader": {
            "double": 500,
            "hr": 630,
            "h": -155,
            "single": 120,
            "triple": 3500
        },
        "isaac paredes": {
            "double": 500,
            "hr": 400,
            "h": -175,
            "single": 115
        },
        "anthony volpe": {
            "double": 500,
            "hr": 630,
            "h": -145,
            "single": 135,
            "triple": 3000
        },
        "giancarlo stanton": {
            "double": 550,
            "hr": 330,
            "h": -160,
            "single": 145
        },
        "luke raley": {
            "double": 550,
            "hr": 430,
            "h": -160,
            "single": 130,
            "triple": 2900
        },
        "brandon lowe": {
            "double": 600,
            "hr": 420,
            "h": -165,
            "single": 115,
            "triple": 4300
        },
        "kyle higashioka": {
            "double": 650,
            "hr": 680,
            "h": -115,
            "single": 155
        },
        "anthony rizzo": {
            "double": 650,
            "hr": 680,
            "h": -160,
            "single": -105
        },
        "christian bethancourt": {
            "double": 650,
            "hr": 680,
            "h": -140,
            "single": 115
        },
        "josh lowe": {
            "double": 650,
            "hr": 560,
            "h": -135,
            "single": 130,
            "triple": 4300
        },
        "jose siri": {
            "double": 700,
            "hr": 630,
            "h": -120,
            "single": 150,
            "triple": 4500
        }
    },
    "bal @ tor": {
        "yusei kikuchi": {
            "k": "o6.5 -122/-104"
        },
        "grayson rodriguez": {
            "k": "o4.5 -146/114"
        },
        "george springer": {
            "h": -290,
            "hr": 450,
            "triple": 4800,
            "single": -140,
            "double": 280
        },
        "whit merrifield": {
            "h": -280,
            "hr": 870,
            "triple": 4000,
            "single": -165,
            "double": 310
        },
        "vladimir guerrero": {
            "h": -270,
            "hr": 340,
            "single": -125,
            "double": 310
        },
        "ryan mountcastle": {
            "h": -260,
            "hr": 400,
            "triple": 4500,
            "single": -115,
            "double": 290
        },
        "austin hays": {
            "h": -230,
            "hr": 450,
            "triple": 3900,
            "single": -110,
            "double": 320
        },
        "ramon urias": {
            "h": -220,
            "hr": 600,
            "single": -115,
            "double": 330
        },
        "jordan westburg": {
            "h": -210,
            "hr": 680,
            "triple": 4500,
            "single": -110,
            "double": 340
        },
        "danny jansen": {
            "h": -210,
            "hr": 470,
            "single": -105,
            "double": 290
        },
        "adley rutschman": {
            "h": -210,
            "hr": 630,
            "single": -110,
            "double": 330
        },
        "matt chapman": {
            "h": -195,
            "hr": 440,
            "single": 110,
            "double": 360
        },
        "gunnar henderson": {
            "h": -190,
            "hr": 500,
            "triple": 1600,
            "single": 105,
            "double": 470
        },
        "daulton varsho": {
            "h": -185,
            "hr": 480,
            "triple": 4400,
            "single": 105,
            "double": 480
        },
        "anthony santander": {
            "h": -175,
            "hr": 400,
            "single": 125,
            "double": 420
        },
        "paul dejong": {
            "h": -160,
            "hr": 460,
            "single": 130,
            "double": 440
        },
        "jorge mateo": {
            "h": -155,
            "hr": 700,
            "triple": 3100,
            "single": 125,
            "double": 400
        },
        "kevin kiermaier": {
            "h": -155,
            "hr": 870,
            "triple": 2300,
            "single": 115,
            "double": 500
        },
        "brandon belt": {
            "h": -140,
            "hr": 420,
            "single": 165,
            "double": 550
        },
        "ryan mckenna": {
            "h": -135,
            "hr": 900,
            "triple": 4500,
            "single": 135,
            "double": 480
        }
    },
    "min @ stl": {
        "joe ryan": {
            "k": "o5.5 -152/120"
        },
        "byron buxton": {
            "hr": 340,
            "single": -105,
            "h": -220,
            "double": 430,
            "triple": 2800
        },
        "paul goldschmidt": {
            "hr": 400,
            "single": -110,
            "h": -220,
            "double": 420
        },
        "nolan arenado": {
            "hr": 420,
            "single": -110,
            "h": -220,
            "double": 390,
            "triple": 4200
        },
        "joey gallo": {
            "hr": 430,
            "single": 195,
            "h": -110,
            "double": 800
        },
        "nolan gorman": {
            "hr": 450,
            "single": 140,
            "h": -155,
            "double": 500
        },
        "carlos correa": {
            "hr": 500,
            "single": -155,
            "h": -270,
            "double": 360,
            "triple": 3800
        },
        "lars nootbaar": {
            "hr": 500,
            "single": -110,
            "h": -210,
            "double": 420,
            "triple": 4000
        },
        "tyler oneill": {
            "hr": 500,
            "single": 130,
            "h": -160,
            "double": 470,
            "triple": 4400
        },
        "willson contreras": {
            "hr": 520,
            "single": 110,
            "h": -180,
            "double": 450
        },
        "jorge polanco": {
            "hr": 540,
            "single": -140,
            "h": -240,
            "double": 380,
            "triple": 4700
        },
        "max kepler": {
            "hr": 560,
            "single": -145,
            "h": -240,
            "double": 410,
            "triple": 4400
        },
        "matt wallner": {
            "hr": 600,
            "single": -105,
            "h": -180,
            "double": 500,
            "triple": 2500
        },
        "edouard julien": {
            "hr": 600,
            "single": -150,
            "h": -250,
            "double": 420,
            "triple": 2300
        },
        "jordan walker": {
            "hr": 600,
            "single": 105,
            "h": -180,
            "double": 500,
            "triple": 1700
        },
        "ryan jeffers": {
            "hr": 700,
            "single": 105,
            "h": -170,
            "double": 450,
            "triple": 4900
        },
        "michael taylor": {
            "hr": 800,
            "single": -120,
            "h": -190,
            "double": 450,
            "triple": 4000
        },
        "dylan carlson": {
            "hr": 870,
            "single": 130,
            "h": -135,
            "double": 500,
            "triple": 3300
        },
        "tommy edman": {
            "hr": 900,
            "single": -105,
            "h": -175,
            "double": 430,
            "triple": 2900
        }
    },
    "cin @ chc": {
        "drew smyly": {
            "k": "o5.5 110/-140"
        },
        "brandon williamson": {
            "k": "o3.5 -140/110"
        },
        "nico hoerner": {
            "h": -320,
            "hr": 750,
            "triple": 2000,
            "double": 310,
            "single": -180
        },
        "matt mclain": {
            "h": -290,
            "hr": 450,
            "triple": 1700,
            "double": 270,
            "single": -135
        },
        "seiya suzuki": {
            "h": -270,
            "hr": 520,
            "triple": 2100,
            "double": 320,
            "single": -130
        },
        "spencer steer": {
            "h": -270,
            "hr": 390,
            "triple": 2300,
            "double": 310,
            "single": -125
        },
        "elly de la cruz": {
            "h": -260,
            "hr": 520,
            "triple": 1100,
            "double": 320,
            "single": -125
        },
        "nick senzel": {
            "h": -250,
            "hr": 630,
            "triple": 3500,
            "double": 320,
            "single": -140
        },
        "christian encarnacion strand": {
            "h": -240,
            "hr": 600,
            "triple": 3100,
            "double": 380,
            "single": -135
        },
        "kevin newman": {
            "h": -240,
            "hr": 900,
            "triple": 3000,
            "double": 380,
            "single": -155
        },
        "yan gomes": {
            "h": -240,
            "hr": 540,
            "triple": 3700,
            "double": 380,
            "single": -135
        },
        "dansby swanson": {
            "h": -240,
            "hr": 420,
            "triple": 3000,
            "double": 350,
            "single": -110
        },
        "cody bellinger": {
            "h": -230,
            "hr": 520,
            "triple": 3600,
            "double": 360,
            "single": -120
        },
        "nick madrigal": {
            "h": -230,
            "hr": 1060,
            "triple": 2500,
            "double": 400,
            "single": -150
        },
        "jeimer candelario": {
            "h": -220,
            "hr": 540,
            "triple": 3200,
            "double": 360,
            "single": -110
        },
        "tyler stephenson": {
            "h": -210,
            "hr": 800,
            "triple": 4800,
            "double": 380,
            "single": -120
        },
        "ian happ": {
            "h": -200,
            "hr": 560,
            "triple": 2800,
            "double": 370,
            "single": -105
        },
        "christopher morel": {
            "h": -190,
            "hr": 400,
            "triple": 2600,
            "double": 410,
            "single": 120
        },
        "joey votto": {
            "h": -180,
            "hr": 500,
            "double": 490,
            "single": 100
        },
        "stuart fairchild": {
            "h": -125,
            "hr": 800,
            "triple": 2100,
            "double": 500,
            "single": 155
        }
    },
    "chw @ tex": {
        "dylan cease": {
            "k": "o6.5 -126/-102"
        },
        "dane dunning": {
            "k": "o4.5 -108/-118"
        },
        "tim anderson": {
            "single": -190,
            "hr": 900,
            "h": -290,
            "triple": 4000,
            "double": 370
        },
        "andrew benintendi": {
            "single": -155,
            "hr": 870,
            "h": -230,
            "triple": 4000,
            "double": 430
        },
        "travis jankowski": {
            "single": -140,
            "hr": 1100,
            "h": -200,
            "triple": 2900,
            "double": 450
        },
        "oscar colas": {
            "single": -130,
            "hr": 800,
            "h": -195,
            "triple": 3200,
            "double": 550
        },
        "luis robert": {
            "single": -130,
            "hr": 440,
            "h": -240,
            "double": 390
        },
        "yoan moncada": {
            "single": -125,
            "hr": 630,
            "h": -220,
            "triple": 3000,
            "double": 380
        },
        "eloy jimenez": {
            "single": -125,
            "hr": 470,
            "h": -240,
            "double": 390
        },
        "andrew vaughn": {
            "single": -125,
            "hr": 600,
            "h": -210,
            "double": 430
        },
        "nathaniel lowe": {
            "single": -120,
            "hr": 560,
            "h": -210,
            "triple": 4600,
            "double": 430
        },
        "marcus semien": {
            "single": -115,
            "hr": 470,
            "h": -220,
            "triple": 3100,
            "double": 420
        },
        "elvis andrus": {
            "single": -105,
            "hr": 900,
            "h": -160,
            "triple": 4200,
            "double": 500
        },
        "leody taveras": {
            "single": 100,
            "hr": 870,
            "h": -170,
            "triple": 3000,
            "double": 470
        },
        "ezequiel duran": {
            "single": 110,
            "hr": 750,
            "h": -160,
            "triple": 3700,
            "double": 500
        },
        "josh jung": {
            "single": 110,
            "hr": 520,
            "h": -170,
            "triple": 4800,
            "double": 500
        },
        "robbie grossman": {
            "single": 120,
            "hr": 680,
            "h": -150,
            "triple": 4000,
            "double": 550
        },
        "adolis garcia": {
            "single": 125,
            "hr": 420,
            "h": -170,
            "triple": 3200,
            "double": 500
        },
        "mitch garver": {
            "single": 145,
            "hr": 520,
            "h": -130,
            "double": 650
        },
        "seby zavala": {
            "single": 150,
            "hr": 750,
            "h": -115,
            "double": 650
        }
    },
    "nym @ kc": {
        "kodai senga": {
            "k": "o6.5 120/-152"
        },
        "pete alonso": {
            "hr": 310,
            "double": 350,
            "h": -250,
            "triple": 3900,
            "single": -105
        },
        "francisco alvarez": {
            "hr": 330,
            "double": 380,
            "h": -240,
            "triple": 4500,
            "single": -105
        },
        "francisco lindor": {
            "hr": 430,
            "double": 300,
            "h": -260,
            "triple": 2200,
            "single": -120
        },
        "salvador perez": {
            "hr": 500,
            "double": 370,
            "h": -200,
            "single": 100
        },
        "rafael ortega": {
            "hr": 500,
            "double": 430,
            "h": -170,
            "triple": 2900,
            "single": 120
        },
        "bobby witt": {
            "hr": 520,
            "double": 310,
            "h": -280,
            "triple": 1500,
            "single": -135
        },
        "daniel vogelbach": {
            "hr": 560,
            "double": 460,
            "h": -165,
            "single": 115
        },
        "brandon nimmo": {
            "hr": 600,
            "double": 340,
            "h": -290,
            "triple": 1400,
            "single": -160
        },
        "mj melendez": {
            "hr": 630,
            "double": 470,
            "h": -175,
            "triple": 3800,
            "single": 100
        },
        "brett baty": {
            "hr": 680,
            "double": 360,
            "h": -230,
            "triple": 3100,
            "single": -135
        },
        "starling marte": {
            "hr": 680,
            "double": 370,
            "h": -220,
            "triple": 2200,
            "single": -125
        },
        "matt beaty": {
            "hr": 830,
            "double": 410,
            "h": -160,
            "triple": 4400,
            "single": 110
        },
        "michael massey": {
            "hr": 870,
            "double": 500,
            "h": -165,
            "triple": 2800,
            "single": 100
        },
        "edward olivares": {
            "hr": 870,
            "double": 340,
            "h": -210,
            "triple": 1800,
            "single": -105
        },
        "jeff mcneil": {
            "hr": 900,
            "double": 310,
            "h": -330,
            "triple": 2700,
            "single": -200
        },
        "drew waters": {
            "hr": 1000,
            "double": 500,
            "h": -150,
            "triple": 1400,
            "single": 115
        },
        "maikel garcia": {
            "hr": 1000,
            "double": 310,
            "h": -290,
            "triple": 1100,
            "single": -160
        },
        "kyle isbel": {
            "hr": 1000,
            "double": 420,
            "h": -170,
            "triple": 2200,
            "single": 105
        }
    },
    "ari @ sf": {
        "logan webb": {
            "k": "o5.5 120/-150"
        },
        "joc pederson": {
            "hr": 420,
            "triple": 2500,
            "single": -105,
            "double": 360,
            "h": -230
        },
        "wilmer flores": {
            "hr": 470,
            "single": -130,
            "double": 280,
            "h": -260
        },
        "michael conforto": {
            "hr": 500,
            "triple": 4300,
            "single": -110,
            "double": 360,
            "h": -220
        },
        "lamonte wade": {
            "hr": 500,
            "triple": 2800,
            "single": -105,
            "double": 360,
            "h": -210
        },
        "corbin carroll": {
            "hr": 560,
            "triple": 1400,
            "single": -170,
            "double": 360,
            "h": -290
        },
        "jd davis": {
            "hr": 560,
            "single": -105,
            "double": 340,
            "h": -210
        },
        "brandon crawford": {
            "hr": 630,
            "triple": 3600,
            "single": 115,
            "double": 430,
            "h": -165
        },
        "ketel marte": {
            "hr": 680,
            "triple": 1800,
            "single": -135,
            "double": 310,
            "h": -260
        },
        "christian walker": {
            "hr": 700,
            "single": -120,
            "double": 350,
            "h": -210
        },
        "isan diaz": {
            "hr": 750,
            "triple": 2900,
            "single": 135,
            "double": 550,
            "h": -135
        },
        "lourdes gurriel": {
            "hr": 900,
            "triple": 3700,
            "single": -145,
            "double": 300,
            "h": -250
        },
        "luis matos": {
            "hr": 900,
            "triple": 1400,
            "single": -135,
            "double": 400,
            "h": -230
        },
        "patrick bailey": {
            "hr": 900,
            "triple": 3200,
            "single": -105,
            "double": 330,
            "h": -185
        },
        "jace peterson": {
            "hr": 1000,
            "triple": 3000,
            "single": 100,
            "double": 480,
            "h": -160
        },
        "alek thomas": {
            "hr": 1060,
            "triple": 2300,
            "single": 100,
            "double": 450,
            "h": -165
        },
        "geraldo perdomo": {
            "hr": 1300,
            "triple": 2400,
            "single": -135,
            "double": 380,
            "h": -210
        },
        "jose herrera": {
            "hr": 1300,
            "triple": 3800,
            "single": 110,
            "double": 500,
            "h": -140
        },
        "jake mccarthy": {
            "hr": 1500,
            "triple": 1600,
            "single": -130,
            "double": 460,
            "h": -190
        }
    },
    "oak @ lad": {
        "hogan harris": {
            "k": "o4.5 120/-154"
        },
        "tony gonsolin": {
            "k": "o5.5 -130/102"
        },
        "amed rosario": {
            "triple": 3400,
            "h": -330,
            "double": 280,
            "single": -185,
            "hr": 680
        },
        "shea langeliers": {
            "triple": 3500,
            "h": -155,
            "double": 490,
            "single": 130,
            "hr": 520
        },
        "zack gelof": {
            "triple": 3600,
            "h": -170,
            "double": 390,
            "single": 115,
            "hr": 520
        },
        "cody thomas": {
            "triple": 4000,
            "h": -180,
            "double": 440,
            "single": 110,
            "hr": 470
        },
        "tony kemp": {
            "triple": 4100,
            "h": -160,
            "double": 440,
            "single": -105,
            "hr": 1200
        },
        "chris taylor": {
            "triple": 4700,
            "h": -160,
            "double": 430,
            "single": 135,
            "hr": 480
        },
        "tyler soderstrom": {
            "triple": 4900,
            "h": -135,
            "double": 650,
            "single": 130,
            "hr": 750
        },
        "mookie betts": {
            "h": -310,
            "double": 270,
            "single": -130,
            "hr": 285
        },
        "freddie freeman": {
            "h": -300,
            "double": 270,
            "single": -135,
            "hr": 360
        },
        "will smith": {
            "h": -270,
            "double": 280,
            "single": -125,
            "hr": 420
        },
        "max muncy": {
            "h": -210,
            "double": 440,
            "single": 110,
            "hr": 310
        },
        "miguel rojas": {
            "h": -210,
            "double": 400,
            "single": -135,
            "hr": 900
        },
        "austin barnes": {
            "h": -200,
            "double": 380,
            "single": -105,
            "hr": 540
        },
        "seth brown": {
            "h": -185,
            "double": 490,
            "single": 110,
            "hr": 390
        },
        "jace peterson": {
            "h": -170,
            "double": 460,
            "single": -110,
            "hr": 870
        },
        "enrique hernandez": {
            "h": -170,
            "double": 380,
            "single": 110,
            "hr": 700
        },
        "jj bleday": {
            "h": -155,
            "double": 490,
            "single": 130,
            "hr": 520
        },
        "nick allen": {
            "h": -125,
            "double": 550,
            "single": 115,
            "hr": 1400
        }
    }
}